xlib_hotkeys/__init__.py
xlib_hotkeys/__main__.py
xlib_hotkeys-2024.3.0.dist-info/LICENSE.md
xlib_hotkeys-2024.3.0.dist-info/METADATA
xlib_hotkeys-2024.3.0.dist-info/WHEEL
xlib_hotkeys-2024.3.0.dist-info/entry_points.txt
xlib_hotkeys-2024.3.0.dist-info/top_level.txt
xlib_hotkeys-2024.3.0.dist-info/RECORD
