Metadata-Version: 2.1
Name: xlib-hotkeys
Version: 2024.3.0
Summary: Register Keyboard Hotkeys to a callback function
Home-page: https://github.com/bkbilly/xlib_hotkeys
Author-email: bkbilly <bkbilly@hotmail.com>
Project-URL: Source Code, https://github.com/bkbilly/xlib_hotkeys
Keywords: keyboard,hotkeys
Classifier: Programming Language :: Python :: 3
Classifier: License :: OSI Approved :: MIT License
Classifier: Operating System :: Unix
Requires-Python: >=3.7.0
License-File: LICENSE.md
Requires-Dist: python-xlib (>=0.33)
